[{"title":"Bottles","price":"1000.99","imageUrl":"https://images-na.ssl-images-amazon.com/images/I/71d6uaO0LBL._SL1500_.jpg","description":"Amazing bottle","id":"1234123412"},{"title":"Beer","price":"1500","imageUrl":"https://images-na.ssl-images-amazon.com/images/I/81hqcrj2MbL._SL1500_.jpg","description":"alkcasdn asdnv lajsdv andv landv ladn v","id":"0.3913553319896135"},{"title":"Dell Laptop","price":"35000","imageUrl":"https://images-na.ssl-images-amazon.com/images/I/81kctE-tR4L._SL1500_.jpg","description":"Amazing next gen laptop","id":"0.028670209197266594"},{"title":"Cycle","price":"24000","imageUrl":"https://contents.mediadecathlon.com/p1342363/k$10bdd7c92aa9e1a33aee8efb9a25907d/btwin-rockrider-100-8-12years-kids-cycle.jpg?&f=250x250","description":"KIdjvk fvksjnflvjs fv svl flvsjef vlsjenf ","id":"0.2740955087003758"},{"title":"Herculus","price":"30000","imageUrl":"https://5.imimg.com/data5/BL/EC/GLADMIN-29154336/tz-130-hercules-top-speed-cycle-500x500.png","description":"ldkfv sdfvn aldfn valdfn vlsdfn vlsdf ","id":"0.15664038055220253"},{"title":"Bottles","price":"1000.99","imageUrl":"https://images-na.ssl-images-amazon.com/images/I/71d6uaO0LBL._SL1500_.jpg","description":"Amazing bottle","id":"1234123412"},{"title":"Library","price":12000,"imageUrl":"https://encrypted-tbn0.gstatic.com/images?q=tbn:ANd9GcTBbA3XfqKc4vKmGV-TQnB-XLNYKdSadx6UYqwAz5QYOL46_dmhXg","description":"dfvsdf","id":"0.30368248429572686"}]